SETMOK_API/SETMOKE_API.py
SETMOK_API/__init__.py
SETMOK_API/entities/Mention.py
SETMOK_API/entities/Retweeter.py
SETMOK_API/entities/User.py
SETMOK_API/entities/__init__.py
SETMOK_API/src/GooglePlusDataRetreivel.py
SETMOK_API/src/TwitterDataRetrievel.py
SETMOK_API/src/__init__.py
SETMOK_API/util/ConfigurationParser.py
SETMOK_API/util/Mysql.py
SETMOK_API/util/SchedulerScript.py
SETMOK_API/util/__init__.py
SET_MOKE-0.5.dist-info/DESCRIPTION.rst
SET_MOKE-0.5.dist-info/METADATA
SET_MOKE-0.5.dist-info/RECORD
SET_MOKE-0.5.dist-info/WHEEL
SET_MOKE-0.5.dist-info/metadata.json
SET_MOKE-0.5.dist-info/top_level.txt
