Metadata-Version: 2.0
Name: SET-MOKE
Version: 0.5
Summary: An API for social media data extraction
Home-page: https://github.com/rehabshahzadi/SETMOK_API
Author: rehab shahzadi
Author-email: rehab.shahzadi@kics.edu.pk
License: UNKNOWN
Platform: UNKNOWN
Classifier: Programming Language :: Python :: 3
Classifier: Operating System :: OS Independent
Requires-Dist: google-api-python-client
Requires-Dist: moment
Requires-Dist: pymysql
Requires-Dist: tweepy (==3.6.0)
Requires-Dist: twitter (==1.18.0)
